lazysdk/__init__.py
lazysdk/lazyCrypto.py
lazysdk/lazySQLite.py
lazysdk/lazyTinyDB.py
lazysdk/lazy_header.py
lazysdk/lazy_id_card.py
lazysdk/lazy_input.py
lazysdk/lazybase64.py
lazysdk/lazybeep.py
lazysdk/lazycache.py
lazysdk/lazychromedriver.py
lazysdk/lazydecode.py
lazysdk/lazydict.py
lazysdk/lazyenv.py
lazysdk/lazyexcel.py
lazysdk/lazyfile.py
lazysdk/lazyflask.py
lazysdk/lazyhash.py
lazysdk/lazyhtml.py
lazysdk/lazyid.py
lazysdk/lazyinfo.py
lazysdk/lazyip.py
lazysdk/lazyjson.py
lazysdk/lazylist.py
lazysdk/lazym3u8.py
lazysdk/lazymd5.py
lazysdk/lazypath.py
lazysdk/lazyprocess.py
lazysdk/lazyproxies.py
lazysdk/lazyrandom.py
lazysdk/lazyre.py
lazysdk/lazyredis.py
lazysdk/lazyrequests.py
lazysdk/lazytext.py
lazysdk/lazytime.py
lazysdk/lazyurl.py
lazysdk/lazywebhook.py
lazysdk/lazywifi.py
lazysdk/lazyxml.py
lazysdk/showdata.py
lazysdk-0.2.20.dist-info/licenses/LICENSE
test/__init__.py
test/test.py
test/test2.py
test/test_driver.py
lazysdk-0.2.20.dist-info/METADATA
lazysdk-0.2.20.dist-info/WHEEL
lazysdk-0.2.20.dist-info/top_level.txt
lazysdk-0.2.20.dist-info/RECORD
