Metadata-Version: 2.4
Name: lazysdk
Version: 0.2.20
Summary: 基于Python的懒人包
Home-page: https://gitee.com/ZeroSeeker/lazysdk
Author: ZeroSeeker
Author-email: zeroseeker@foxmail.com
Classifier: Programming Language :: Python :: 3
Classifier: License :: OSI Approved :: MIT License
Classifier: Operating System :: OS Independent
License-File: LICENSE
Requires-Dist: showlog>=0.0.6
Requires-Dist: requests>=2.31.0
Requires-Dist: envx>=1.0.1
Requires-Dist: pytz==2022.1
Requires-Dist: ua_parser==0.10.0
Requires-Dist: openpyxl==3.0.9
Requires-Dist: xlrd==2.0.1
Requires-Dist: m3u8==3.5.0
Requires-Dist: pycryptodome==3.10.1
Requires-Dist: filetype==1.2.0
Requires-Dist: netifaces==0.11.0
Requires-Dist: user_agents==2.2.0
Requires-Dist: rich>=13.5.2
Requires-Dist: urllib3==1.26.10
Dynamic: author
Dynamic: author-email
Dynamic: classifier
Dynamic: description
Dynamic: description-content-type
Dynamic: home-page
Dynamic: license-file
Dynamic: requires-dist
Dynamic: summary
